{
    "link": null,
    "title": "Dragon Age: Origins \u2013 Ultimate Edition \u2013 GOG Version",
    "first_img": "https://i78.fastpic.ru/big/2016/0724/15/9b541d316d0f1c258ab63fab0968d015.jpg",
    "second_img": [],
    "body": "<div ><h2>Dragon Age: Origins \u2013 Ultimate Edition \u2013 GOG Version</h2><p ><div><a href=\"http://en.riotpixels.com/games/dragon-age-origins/\"><img class=\"alignleft\" src=\"https://i78.fastpic.ru/big/2016/0724/15/9b541d316d0f1c258ab63fab0968d015.jpg\"></a></div><br>Company: <strong>Electronic Arts</strong><br>Languages: <strong>RUS/ENG/MULTI9</strong><br>Original Size: <strong>22.1 GB</strong><br>Repack Size: <strong>from 8.7 GB</strong> [Selective Download]</p><h3>Download Mirrors</h3><ul><li><a href=\"http://extratorrent.cc/torrent/5065315\" target=\"_blank\">ExtraTorrent</a> [<a href=\"magnet:?xt=urn:btih:feeb2071693075dd9b7638afadfab678dd1245b2\">magnet</a>] [<a href=\"http://sendfile.su/1252677\" target=\"_blank\">.torrent file only</a>] (MULTI9)</li><li><a href=\"http://tapochek.net/viewtopic.php?t=190365\" target=\"_blank\">Tapochek.net</a> (ENG/RUS)</li><li><a href=\"http://free-torrents.org/forum/viewtopic.php?t=213154\" target=\"_blank\">FreeTorrents</a> (ENG/RUS)</li><li><a href=\"http://rutor.info/torrent/515789/dragon-age-origins-ultimate-edition-v-1.05-vse-dlc-2009-pc-repack-ot-fitgirl\" target=\"_blank\">RuTor</a> [<a href=\"magnet:?xt=urn:btih:662d8a16401260ce80285d3712ebbd13be98a314&amp;dn=rutor.info_Dragon+Age%3A+Origins+-+Ultimate+Edition+%5Bv+1.05+%2B+%D0%B2%D1%81%D0%B5+DLC%5D+%282009%29+PC+%7C+RePack+%D0%BE%D1%82+FitGirl&amp;tr=udp://opentor.org:2710&amp;tr=udp://opentor.org:2710&amp;tr=http://retracker.local/announce\">magnet</a>] (ENG/RUS)</li></ul><h3>Screenshots (Click to enlarge)</h3><p><a target=\"_blank\" href=\"http://en.riotpixels.com/games/dragon-age-origins/screenshots/929/?utm_source=emb-gfx-html&amp;utm_medium=image&amp;utm_campaign=rp-mass\"><img loading=\"lazy\" width=\"320\" height=\"180\" border=\"0\" src=\"https://s01.riotpixels.net/data/09/71/09717801-c45e-49d9-9a33-70f8e14b9367.jpg.240p.jpg\"></a><a target=\"_blank\" href=\"http://en.riotpixels.com/games/dragon-age-origins/screenshots/927/?utm_source=emb-gfx-html&amp;utm_medium=image&amp;utm_campaign=rp-mass\"><img loading=\"lazy\" width=\"320\" height=\"180\" border=\"0\" src=\"https://s01.riotpixels.net/data/d4/5e/d45e4f36-dd65-446d-b90f-743dacb92871.jpg.240p.jpg\"></a><a target=\"_blank\" href=\"http://en.riotpixels.com/games/dragon-age-origins/screenshots/921/?utm_source=emb-gfx-html&amp;utm_medium=image&amp;utm_campaign=rp-mass\"><img loading=\"lazy\" width=\"320\" height=\"180\" border=\"0\" src=\"https://s01.riotpixels.net/data/a0/27/a027508f-c3f3-4024-9159-3dfe4a989e7c.jpg.240p.jpg\"></a><a target=\"_blank\" href=\"http://en.riotpixels.com/games/dragon-age-origins/screenshots/920/?utm_source=emb-gfx-html&amp;utm_medium=image&amp;utm_campaign=rp-mass\"><img loading=\"lazy\" width=\"320\" height=\"180\" border=\"0\" src=\"https://s01.riotpixels.net/data/0f/5f/0f5fbf2f-888b-450d-9b0f-7de393558c43.jpg.240p.jpg\"></a><a target=\"_blank\" href=\"http://en.riotpixels.com/games/dragon-age-origins/screenshots/914/?utm_source=emb-gfx-html&amp;utm_medium=image&amp;utm_campaign=rp-mass\"><img loading=\"lazy\" width=\"320\" height=\"180\" border=\"0\" src=\"https://s01.riotpixels.net/data/6f/1a/6f1afd0e-b78c-4583-b98a-09f7b8e039f8.jpg.240p.jpg\"></a><a target=\"_blank\" href=\"http://en.riotpixels.com/games/dragon-age-origins/screenshots/912/?utm_source=emb-gfx-html&amp;utm_medium=image&amp;utm_campaign=rp-mass\"><img loading=\"lazy\" width=\"320\" height=\"180\" border=\"0\" src=\"https://s01.riotpixels.net/data/ab/4d/ab4d7f3b-dc4c-4647-93fc-2e6a235e7ce2.jpg.240p.jpg\"></a></p>             </div>"
}