{
    "link": null,
    "title": "Hoster Upgrade",
    "first_img": [],
    "second_img": null,
    "body": "<div class=\"entry-content\"><p><img loading=\"lazy\" class=\"aligncenter size-full wp-image-158\" src=\"https://fitgirl-repacks.site/wp-content/uploads/2016/08/amelie12_555.png\" alt=\"amelie12_555\" width=\"555\" height=\"241\" srcset=\"https://fitgirl-repacks.site/wp-content/uploads/2016/08/amelie12_555.png 555w, https://fitgirl-repacks.site/wp-content/uploads/2016/08/amelie12_555-300x130.png 300w\" sizes=\"(max-width: 555px) 100vw, 555px\"></p><p>I\u2019ve changed the hosting machine to a more powerful now. Please report how fast site is now compared to the state it was before.</p><p>Reason for upgrade? WP Stats for today: <span style=\"color: #ff0000;\">32,282 views</span></p>             </div>"
}